chatterbot_io_adapters
