Metadata-Version: 1.1
Name: chatterbot-io-adapters
Version: 0.0.2
Summary: ChatterBots input and output adapters
Home-page: https://github.com/vkosuri/chatterbot-adapters
Author: Mallikarjunarao Kosuri
Author-email: malli.kv2@gmail.com
License: BSD
Download-URL: https://github.com/vkosuri/chatterbot-adapters/tarball/0.0.2
Keywords: ChatterBot,chatbot,chat,bot,adapters
Platform: any
Classifier: Development Status :: 4 - Beta
Classifier: Intended Audience :: Developers
Classifier: License :: OSI Approved :: BSD License
Classifier: Environment :: Console
Classifier: Environment :: Web Environment
Classifier: Operating System :: OS Independent
Classifier: Topic :: Software Development :: Libraries :: Python Modules
Classifier: Topic :: Communications :: Chat
Classifier: Topic :: Internet
Classifier: Programming Language :: Python
Classifier: Programming Language :: Python :: 2.7
Classifier: Programming Language :: Python :: 3
Classifier: Programming Language :: Python :: 3.4
Classifier: Programming Language :: Python :: 3.5
